<?xml version="1.0" encoding="UTF-8"?>

<!-- generated on 01/21/21 12:23:09 by Eclipse SUMO GUI Version 1.7.0
<configuration xmlns:xsi="http://www.w3.org/2001/XMLSchema-instance" xsi:noNamespaceSchemaLocation="http://sumo.dlr.de/xsd/sumoConfiguration.xsd">

    <input>
        <net-file value="data/EVGrid.net.xml"/>
        <route-files value="data/electricvehicles.rou.xml"/>
        <additional-files value="data/EVGrid_additionals.add.xml"/>
    </input>

    <output>
        <battery-output value="data/battery.out.xml"/>
        <battery-output.precision value="4"/>
        <chargingstations-output value="data/EVGrid_chargingstations.xml"/>
        <summary-output value="data/summary-overview.xml"/>
        <tripinfo-output value="tripinfo.xml"/>
    </output>

    <processing>
        <lateral-resolution value="1"/>
    </processing>

    <battery>
        <device.battery.probability value="1"/>
    </battery>

    <traci_server>
        <remote-port value="51978"/>
    </traci_server>

    <gui_only>
        <gui-settings-file value="data/gui-settings.cfg"/>
    </gui_only>

</configuration>
-->

<summary xmlns:xsi="http://www.w3.org/2001/XMLSchema-instance" xsi:noNamespaceSchemaLocation="http://sumo.dlr.de/xsd/summary_file.xsd">
    <step time="0.00" loaded="101" inserted="44" running="44" waiting="57" ended="0" arrived="0" collisions="0" teleports="0" halting="44" stopped="0" meanWaitingTime="0.00" meanTravelTime="-1.00" meanSpeed="0.00" meanSpeedRelative="0.00" duration="9465332"/>
    <step time="1.00" loaded="101" inserted="44" running="44" waiting="57" ended="0" arrived="0" collisions="0" teleports="0" halting="0" stopped="0" meanWaitingTime="0.00" meanTravelTime="-1.00" meanSpeed="1.91" meanSpeedRelative="0.14" duration="9465432"/>
    <step time="2.00" loaded="101" inserted="45" running="45" waiting="56" ended="0" arrived="0" collisions="0" teleports="0" halting="1" stopped="0" meanWaitingTime="0.04" meanTravelTime="-1.00" meanSpeed="3.67" meanSpeedRelative="0.26" duration="9465533"/>
    <step time="3.00" loaded="101" inserted="71" running="71" waiting="30" ended="0" arrived="0" collisions="0" teleports="0" halting="26" stopped="0" meanWaitingTime="1.13" meanTravelTime="-1.00" meanSpeed="3.49" meanSpeedRelative="0.25" duration="9465633"/>
    <step time="4.00" loaded="101" inserted="72" running="72" waiting="29" ended="0" arrived="0" collisions="0" teleports="0" halting="2" stopped="0" meanWaitingTime="1.17" meanTravelTime="-1.00" meanSpeed="5.25" meanSpeedRelative="0.38" duration="9465733"/>
    <step time="5.00" loaded="101" inserted="73" running="73" waiting="28" ended="0" arrived="0" collisions="0" teleports="0" halting="2" stopped="0" meanWaitingTime="1.22" meanTravelTime="-1.00" meanSpeed="6.93" meanSpeedRelative="0.50" duration="9465833"/>
    <step time="6.00" loaded="101" inserted="88" running="88" waiting="13" ended="0" arrived="0" collisions="0" teleports="0" halting="17" stopped="0" meanWaitingTime="2.03" meanTravelTime="-1.00" meanSpeed="7.15" meanSpeedRelative="0.51" duration="9465933"/>
    <step time="7.00" loaded="101" inserted="88" running="88" waiting="13" ended="0" arrived="0" collisions="0" teleports="0" halting="3" stopped="0" meanWaitingTime="2.03" meanTravelTime="-1.00" meanSpeed="8.59" meanSpeedRelative="0.62" duration="9466033"/>
    <step time="8.00" loaded="101" inserted="89" running="89" waiting="12" ended="0" arrived="0" collisions="0" teleports="0" halting="4" stopped="0" meanWaitingTime="2.10" meanTravelTime="-1.00" meanSpeed="9.50" meanSpeedRelative="0.68" duration="9466134"/>
    <step time="9.00" loaded="101" inserted="96" running="96" waiting="5" ended="0" arrived="0" collisions="0" teleports="0" halting="10" stopped="0" meanWaitingTime="2.60" meanTravelTime="-1.00" meanSpeed="9.74" meanSpeedRelative="0.70" duration="9466234"/>
    <step time="10.00" loaded="101" inserted="96" running="96" waiting="5" ended="0" arrived="0" collisions="0" teleports="0" halting="4" stopped="0" meanWaitingTime="2.60" meanTravelTime="-1.00" meanSpeed="10.57" meanSpeedRelative="0.76" duration="9466333"/>
    <step time="11.00" loaded="101" inserted="96" running="96" waiting="5" ended="0" arrived="0" collisions="0" teleports="0" halting="4" stopped="0" meanWaitingTime="2.60" meanTravelTime="-1.00" meanSpeed="11.20" meanSpeedRelative="0.81" duration="9466434"/>
    <step time="12.00" loaded="101" inserted="98" running="98" waiting="3" ended="0" arrived="0" collisions="0" teleports="0" halting="5" stopped="0" meanWaitingTime="2.80" meanTravelTime="-1.00" meanSpeed="11.42" meanSpeedRelative="0.82" duration="9466535"/>
    <step time="13.00" loaded="101" inserted="98" running="98" waiting="3" ended="0" arrived="0" collisions="0" teleports="0" halting="2" stopped="0" meanWaitingTime="2.80" meanTravelTime="-1.00" meanSpeed="11.75" meanSpeedRelative="0.85" duration="9466636"/>
    <step time="14.00" loaded="101" inserted="98" running="98" waiting="3" ended="0" arrived="0" collisions="0" teleports="0" halting="2" stopped="0" meanWaitingTime="2.80" meanTravelTime="-1.00" meanSpeed="12.11" meanSpeedRelative="0.87" duration="9466736"/>
    <step time="15.00" loaded="101" inserted="98" running="98" waiting="3" ended="0" arrived="0" collisions="0" teleports="0" halting="1" stopped="0" meanWaitingTime="2.80" meanTravelTime="-1.00" meanSpeed="12.36" meanSpeedRelative="0.89" duration="9466837"/>
    <step time="16.00" loaded="101" inserted="98" running="98" waiting="3" ended="0" arrived="0" collisions="0" teleports="0" halting="0" stopped="0" meanWaitingTime="2.80" meanTravelTime="-1.00" meanSpeed="12.46" meanSpeedRelative="0.90" duration="9466937"/>
    <step time="17.00" loaded="101" inserted="98" running="98" waiting="3" ended="0" arrived="0" collisions="0" teleports="0" halting="0" stopped="0" meanWaitingTime="2.80" meanTravelTime="-1.00" meanSpeed="12.57" meanSpeedRelative="0.90" duration="9467038"/>
    <step time="18.00" loaded="101" inserted="98" running="98" waiting="3" ended="0" arrived="0" collisions="0" teleports="0" halting="0" stopped="0" meanWaitingTime="2.80" meanTravelTime="-1.00" meanSpeed="12.60" meanSpeedRelative="0.91" duration="9467138"/>
    <step time="19.00" loaded="101" inserted="99" running="98" waiting="2" ended="1" arrived="1" collisions="0" teleports="0" halting="1" stopped="0" meanWaitingTime="2.96" meanTravelTime="15.00" meanSpeed="12.12" meanSpeedRelative="0.87" duration="9467239"/>
    <step time="20.00" loaded="101" inserted="100" running="99" waiting="1" ended="1" arrived="1" collisions="0" teleports="0" halting="1" stopped="0" meanWaitingTime="3.13" meanTravelTime="15.00" meanSpeed="11.19" meanSpeedRelative="0.81" duration="9467338"/>
    <step time="21.00" loaded="101" inserted="100" running="98" waiting="1" ended="2" arrived="2" collisions="0" teleports="0" halting="0" stopped="0" meanWaitingTime="3.13" meanTravelTime="16.50" meanSpeed="10.29" meanSpeedRelative="0.74" duration="9467439"/>
    <step time="22.00" loaded="101" inserted="100" running="98" waiting="1" ended="2" arrived="2" collisions="0" teleports="0" halting="1" stopped="0" meanWaitingTime="3.13" meanTravelTime="16.50" meanSpeed="9.44" meanSpeedRelative="0.68" duration="9467539"/>
    <step time="23.00" loaded="101" inserted="101" running="99" waiting="0" ended="2" arrived="2" collisions="0" teleports="0" halting="5" stopped="0" meanWaitingTime="3.33" meanTravelTime="16.50" meanSpeed="8.86" meanSpeedRelative="0.64" duration="9467642"/>
    <step time="24.00" loaded="101" inserted="101" running="99" waiting="0" ended="2" arrived="2" collisions="0" teleports="0" halting="5" stopped="0" meanWaitingTime="3.33" meanTravelTime="16.50" meanSpeed="8.57" meanSpeedRelative="0.62" duration="9467741"/>
    <step time="25.00" loaded="101" inserted="101" running="99" waiting="0" ended="2" arrived="2" collisions="0" teleports="0" halting="6" stopped="0" meanWaitingTime="3.33" meanTravelTime="16.50" meanSpeed="8.34" meanSpeedRelative="0.60" duration="9467843"/>
    <step time="26.00" loaded="101" inserted="101" running="99" waiting="0" ended="2" arrived="2" collisions="0" teleports="0" halting="7" stopped="0" meanWaitingTime="3.33" meanTravelTime="16.50" meanSpeed="8.37" meanSpeedRelative="0.60" duration="9467942"/>
    <step time="27.00" loaded="101" inserted="101" running="99" waiting="0" ended="2" arrived="2" collisions="0" teleports="0" halting="12" stopped="0" meanWaitingTime="3.33" meanTravelTime="16.50" meanSpeed="8.26" meanSpeedRelative="0.59" duration="9468043"/>
    <step time="28.00" loaded="101" inserted="101" running="98" waiting="0" ended="3" arrived="3" collisions="0" teleports="0" halting="12" stopped="0" meanWaitingTime="3.33" meanTravelTime="18.33" meanSpeed="8.32" meanSpeedRelative="0.60" duration="9468142"/>
    <step time="29.00" loaded="101" inserted="101" running="98" waiting="0" ended="3" arrived="3" collisions="0" teleports="0" halting="17" stopped="0" meanWaitingTime="3.33" meanTravelTime="18.33" meanSpeed="8.45" meanSpeedRelative="0.61" duration="9468242"/>
    <step time="30.00" loaded="101" inserted="101" running="98" waiting="0" ended="3" arrived="3" collisions="0" teleports="0" halting="16" stopped="0" meanWaitingTime="3.33" meanTravelTime="18.33" meanSpeed="8.70" meanSpeedRelative="0.63" duration="9468343"/>
    <step time="31.00" loaded="101" inserted="101" running="98" waiting="0" ended="3" arrived="3" collisions="0" teleports="0" halting="17" stopped="0" meanWaitingTime="3.33" meanTravelTime="18.33" meanSpeed="8.87" meanSpeedRelative="0.64" duration="9468444"/>
    <step time="32.00" loaded="101" inserted="101" running="98" waiting="0" ended="3" arrived="3" collisions="0" teleports="0" halting="16" stopped="0" meanWaitingTime="3.33" meanTravelTime="18.33" meanSpeed="9.09" meanSpeedRelative="0.65" duration="9468544"/>
    <step time="33.00" loaded="101" inserted="101" running="98" waiting="0" ended="3" arrived="3" collisions="0" teleports="0" halting="16" stopped="0" meanWaitingTime="3.33" meanTravelTime="18.33" meanSpeed="9.37" meanSpeedRelative="0.67" duration="9468644"/>
    <step time="34.00" loaded="101" inserted="101" running="98" waiting="0" ended="3" arrived="3" collisions="0" teleports="0" halting="16" stopped="0" meanWaitingTime="3.33" meanTravelTime="18.33" meanSpeed="9.57" meanSpeedRelative="0.69" duration="9468745"/>
    <step time="35.00" loaded="101" inserted="101" running="98" waiting="0" ended="3" arrived="3" collisions="0" teleports="0" halting="15" stopped="0" meanWaitingTime="3.33" meanTravelTime="18.33" meanSpeed="9.88" meanSpeedRelative="0.71" duration="9468845"/>
    <step time="36.00" loaded="101" inserted="101" running="98" waiting="0" ended="3" arrived="3" collisions="0" teleports="0" halting="14" stopped="0" meanWaitingTime="3.33" meanTravelTime="18.33" meanSpeed="10.10" meanSpeedRelative="0.73" duration="9468945"/>
    <step time="37.00" loaded="101" inserted="101" running="98" waiting="0" ended="3" arrived="3" collisions="0" teleports="0" halting="13" stopped="0" meanWaitingTime="3.33" meanTravelTime="18.33" meanSpeed="10.18" meanSpeedRelative="0.73" duration="9469046"/>
    <step time="38.00" loaded="101" inserted="101" running="98" waiting="0" ended="3" arrived="3" collisions="0" teleports="0" halting="13" stopped="0" meanWaitingTime="3.33" meanTravelTime="18.33" meanSpeed="10.29" meanSpeedRelative="0.74" duration="9469146"/>
    <step time="39.00" loaded="101" inserted="101" running="98" waiting="0" ended="3" arrived="3" collisions="0" teleports="0" halting="13" stopped="0" meanWaitingTime="3.33" meanTravelTime="18.33" meanSpeed="10.29" meanSpeedRelative="0.74" duration="9469247"/>
    <step time="40.00" loaded="101" inserted="101" running="97" waiting="0" ended="4" arrived="4" collisions="0" teleports="0" halting="13" stopped="0" meanWaitingTime="3.33" meanTravelTime="23.75" meanSpeed="10.07" meanSpeedRelative="0.73" duration="9469347"/>
    <step time="41.00" loaded="101" inserted="101" running="97" waiting="0" ended="4" arrived="4" collisions="0" teleports="0" halting="14" stopped="0" meanWaitingTime="3.33" meanTravelTime="23.75" meanSpeed="9.68" meanSpeedRelative="0.70" duration="9469447"/>
    <step time="42.00" loaded="101" inserted="101" running="97" waiting="0" ended="4" arrived="4" collisions="0" teleports="0" halting="16" stopped="0" meanWaitingTime="3.33" meanTravelTime="23.75" meanSpeed="9.38" meanSpeedRelative="0.68" duration="9469548"/>
    <step time="43.00" loaded="101" inserted="101" running="96" waiting="0" ended="5" arrived="5" collisions="0" teleports="0" halting="16" stopped="0" meanWaitingTime="3.33" meanTravelTime="27.60" meanSpeed="9.06" meanSpeedRelative="0.65" duration="9469648"/>
    <step time="44.00" loaded="101" inserted="101" running="96" waiting="0" ended="5" arrived="5" collisions="0" teleports="0" halting="18" stopped="1" meanWaitingTime="3.33" meanTravelTime="27.60" meanSpeed="9.24" meanSpeedRelative="0.67" duration="9469748"/>
    <step time="45.00" loaded="101" inserted="101" running="96" waiting="0" ended="5" arrived="5" collisions="0" teleports="0" halting="18" stopped="1" meanWaitingTime="3.33" meanTravelTime="27.60" meanSpeed="9.14" meanSpeedRelative="0.66" duration="9469849"/>
    <step time="46.00" loaded="101" inserted="101" running="96" waiting="0" ended="5" arrived="5" collisions="0" teleports="0" halting="19" stopped="1" meanWaitingTime="3.33" meanTravelTime="27.60" meanSpeed="9.00" meanSpeedRelative="0.65" duration="9469949"/>
    <step time="47.00" loaded="101" inserted="101" running="96" waiting="0" ended="5" arrived="5" collisions="0" teleports="0" halting="17" stopped="1" meanWaitingTime="3.33" meanTravelTime="27.60" meanSpeed="8.86" meanSpeedRelative="0.64" duration="9470048"/>
    <step time="48.00" loaded="101" inserted="101" running="95" waiting="0" ended="6" arrived="6" collisions="0" teleports="0" halting="18" stopped="1" meanWaitingTime="3.33" meanTravelTime="30.50" meanSpeed="8.51" meanSpeedRelative="0.61" duration="9470148"/>
    <step time="49.00" loaded="101" inserted="101" running="94" waiting="0" ended="7" arrived="7" collisions="0" teleports="0" halting="20" stopped="1" meanWaitingTime="3.33" meanTravelTime="32.29" meanSpeed="8.55" meanSpeedRelative="0.62" duration="9470249"/>
    <step time="50.00" loaded="101" inserted="101" running="93" waiting="0" ended="8" arrived="8" collisions="0" teleports="0" halting="20" stopped="1" meanWaitingTime="3.33" meanTravelTime="34.13" meanSpeed="8.49" meanSpeedRelative="0.61" duration="9470350"/>
    <step time="51.00" loaded="101" inserted="101" running="93" waiting="0" ended="8" arrived="8" collisions="0" teleports="0" halting="19" stopped="1" meanWaitingTime="3.33" meanTravelTime="34.13" meanSpeed="8.36" meanSpeedRelative="0.60" duration="9470450"/>
    <step time="52.00" loaded="101" inserted="101" running="93" waiting="0" ended="8" arrived="8" collisions="0" teleports="0" halting="19" stopped="1" meanWaitingTime="3.33" meanTravelTime="34.13" meanSpeed="8.39" meanSpeedRelative="0.60" duration="9470550"/>
    <step time="53.00" loaded="101" inserted="101" running="93" waiting="0" ended="8" arrived="8" collisions="0" teleports="0" halting="17" stopped="1" meanWaitingTime="3.33" meanTravelTime="34.13" meanSpeed="8.62" meanSpeedRelative="0.62" duration="9470651"/>
    <step time="54.00" loaded="101" inserted="101" running="93" waiting="0" ended="8" arrived="8" collisions="0" teleports="0" halting="17" stopped="0" meanWaitingTime="3.33" meanTravelTime="34.13" meanSpeed="8.75" meanSpeedRelative="0.63" duration="9470751"/>
    <step time="55.00" loaded="101" inserted="101" running="93" waiting="0" ended="8" arrived="8" collisions="0" teleports="0" halting="14" stopped="0" meanWaitingTime="3.33" meanTravelTime="34.13" meanSpeed="9.03" meanSpeedRelative="0.65" duration="9470852"/>
    <step time="56.00" loaded="101" inserted="101" running="92" waiting="0" ended="9" arrived="9" collisions="0" teleports="0" halting="10" stopped="0" meanWaitingTime="3.33" meanTravelTime="36.56" meanSpeed="9.25" meanSpeedRelative="0.67" duration="9470953"/>
    <step time="57.00" loaded="101" inserted="101" running="92" waiting="0" ended="9" arrived="9" collisions="0" teleports="0" halting="9" stopped="0" meanWaitingTime="3.33" meanTravelTime="36.56" meanSpeed="9.39" meanSpeedRelative="0.68" duration="9471053"/>
    <step time="58.00" loaded="101" inserted="101" running="92" waiting="0" ended="9" arrived="9" collisions="0" teleports="0" halting="9" stopped="0" meanWaitingTime="3.33" meanTravelTime="36.56" meanSpeed="9.59" meanSpeedRelative="0.69" duration="9471153"/>
    <step time="59.00" loaded="101" inserted="101" running="92" waiting="0" ended="9" arrived="9" collisions="0" teleports="0" halting="9" stopped="0" meanWaitingTime="3.33" meanTravelTime="36.56" meanSpeed="9.75" meanSpeedRelative="0.70" duration="9471253"/>
    <step time="60.00" loaded="101" inserted="101" running="92" waiting="0" ended="9" arrived="9" collisions="0" teleports="0" halting="7" stopped="0" meanWaitingTime="3.33" meanTravelTime="36.56" meanSpeed="9.83" meanSpeedRelative="0.71" duration="9471354"/>
    <step time="61.00" loaded="101" inserted="101" running="92" waiting="0" ended="9" arrived="9" collisions="0" teleports="0" halting="7" stopped="0" meanWaitingTime="3.33" meanTravelTime="36.56" meanSpeed="9.77" meanSpeedRelative="0.70" duration="9471454"/>
    <step time="62.00" loaded="101" inserted="101" running="92" waiting="0" ended="9" arrived="9" collisions="0" teleports="0" halting="6" stopped="0" meanWaitingTime="3.33" meanTravelTime="36.56" meanSpeed="9.67" meanSpeedRelative="0.70" duration="9471555"/>
    <step time="63.00" loaded="101" inserted="101" running="91" waiting="0" ended="10" arrived="10" collisions="0" teleports="0" halting="7" stopped="0" meanWaitingTime="3.33" meanTravelTime="39.20" meanSpeed="9.43" meanSpeedRelative="0.68" duration="9471655"/>
    <step time="64.00" loaded="101" inserted="101" running="91" waiting="0" ended="10" arrived="10" collisions="0" teleports="0" halting="10" stopped="0" meanWaitingTime="3.33" meanTravelTime="39.20" meanSpeed="9.29" meanSpeedRelative="0.67" duration="9471756"/>
    <step time="65.00" loaded="101" inserted="101" running="91" waiting="0" ended="10" arrived="10" collisions="0" teleports="0" halting="12" stopped="0" meanWaitingTime="3.33" meanTravelTime="39.20" meanSpeed="9.25" meanSpeedRelative="0.67" duration="9471856"/>
    <step time="66.00" loaded="101" inserted="101" running="91" waiting="0" ended="10" arrived="10" collisions="0" teleports="0" halting="14" stopped="0" meanWaitingTime="3.33" meanTravelTime="39.20" meanSpeed="9.16" meanSpeedRelative="0.66" duration="9471957"/>
    <step time="67.00" loaded="101" inserted="101" running="91" waiting="0" ended="10" arrived="10" collisions="0" teleports="0" halting="17" stopped="0" meanWaitingTime="3.33" meanTravelTime="39.20" meanSpeed="9.19" meanSpeedRelative="0.66" duration="9472057"/>
    <step time="68.00" loaded="101" inserted="101" running="91" waiting="0" ended="10" arrived="10" collisions="0" teleports="0" halting="16" stopped="0" meanWaitingTime="3.33" meanTravelTime="39.20" meanSpeed="9.35" meanSpeedRelative="0.67" duration="9472157"/>
    <step time="69.00" loaded="101" inserted="101" running="91" waiting="0" ended="10" arrived="10" collisions="0" teleports="0" halting="14" stopped="0" meanWaitingTime="3.33" meanTravelTime="39.20" meanSpeed="9.48" meanSpeedRelative="0.68" duration="9472258"/>
    <step time="70.00" loaded="101" inserted="101" running="90" waiting="0" ended="11" arrived="11" collisions="0" teleports="0" halting="12" stopped="0" meanWaitingTime="3.33" meanTravelTime="42.00" meanSpeed="9.47" meanSpeedRelative="0.68" duration="9472358"/>
    <step time="71.00" loaded="101" inserted="101" running="90" waiting="0" ended="11" arrived="11" collisions="0" teleports="0" halting="11" stopped="0" meanWaitingTime="3.33" meanTravelTime="42.00" meanSpeed="9.37" meanSpeedRelative="0.67" duration="9472459"/>
    <step time="72.00" loaded="101" inserted="101" running="90" waiting="0" ended="11" arrived="11" collisions="0" teleports="0" halting="10" stopped="0" meanWaitingTime="3.33" meanTravelTime="42.00" meanSpeed="9.26" meanSpeedRelative="0.67" duration="9472559"/>
    <step time="73.00" loaded="101" inserted="101" running="90" waiting="0" ended="11" arrived="11" collisions="0" teleports="0" halting="11" stopped="0" meanWaitingTime="3.33" meanTravelTime="42.00" meanSpeed="9.07" meanSpeedRelative="0.65" duration="9472659"/>
    <step time="74.00" loaded="101" inserted="101" running="87" waiting="0" ended="14" arrived="14" collisions="0" teleports="0" halting="12" stopped="0" meanWaitingTime="3.33" meanTravelTime="48.64" meanSpeed="8.73" meanSpeedRelative="0.63" duration="9472759"/>
    <step time="75.00" loaded="101" inserted="101" running="87" waiting="0" ended="14" arrived="14" collisions="0" teleports="0" halting="13" stopped="0" meanWaitingTime="3.33" meanTravelTime="48.64" meanSpeed="8.56" meanSpeedRelative="0.62" duration="9472860"/>
    <step time="76.00" loaded="101" inserted="101" running="87" waiting="0" ended="14" arrived="14" collisions="0" teleports="0" halting="12" stopped="0" meanWaitingTime="3.33" meanTravelTime="48.64" meanSpeed="8.42" meanSpeedRelative="0.61" duration="9472961"/>
    <step time="77.00" loaded="101" inserted="101" running="87" waiting="0" ended="14" arrived="14" collisions="0" teleports="0" halting="13" stopped="0" meanWaitingTime="3.33" meanTravelTime="48.64" meanSpeed="8.42" meanSpeedRelative="0.61" duration="9473061"/>
    <step time="78.00" loaded="101" inserted="101" running="85" waiting="0" ended="16" arrived="16" collisions="0" teleports="0" halting="13" stopped="0" meanWaitingTime="3.33" meanTravelTime="51.75" meanSpeed="8.43" meanSpeedRelative="0.61" duration="9473162"/>
</summary>
